sindi/__init__.py
sindi/__main__.py
sindi/cli.py
sindi/comparator.py
sindi/comparator_light.py
sindi/config.py
sindi/diversify_predicates.py
sindi/parser.py
sindi/rewriter.py
sindi/simplifier.py
sindi/tokenizer.py
sindi/utils.py
sindi-0.2.0.dist-info/licenses/LICENSE
sindi-0.2.0.dist-info/METADATA
sindi-0.2.0.dist-info/WHEEL
sindi-0.2.0.dist-info/entry_points.txt
sindi-0.2.0.dist-info/top_level.txt
sindi-0.2.0.dist-info/RECORD
