Metadata-Version: 2.4
Name: sindi
Version: 0.2.0
Summary: SInDi: Semantic Invariant Differencing for Solidity Smart Contracts
Home-page: https://github.com/mojtaba-eshghie/Sindi
Author: Mojtaba Eshghie
Author-email: eshghie@kth.se
License: MIT
Project-URL: Source, https://github.com/mojtaba-eshghie/Sindi
Project-URL: Author Website, https://eshghie.com/
Project-URL: Issues, https://github.com/mojtaba-eshghie/Sindi/issues
Classifier: Programming Language :: Python :: 3
Classifier: License :: OSI Approved :: MIT License
Classifier: Operating System :: OS Independent
Requires-Python: >=3.8
License-File: LICENSE
Requires-Dist: sympy>=1.13
Requires-Dist: colorama>=0.4.6
Requires-Dist: pyyaml>=6.0.1
Requires-Dist: z3-solver>=4.12.4.0
Dynamic: author
Dynamic: author-email
Dynamic: classifier
Dynamic: description
Dynamic: description-content-type
Dynamic: home-page
Dynamic: license
Dynamic: license-file
Dynamic: project-url
Dynamic: requires-dist
Dynamic: requires-python
Dynamic: summary
